my_labextension_demo/__init__.py
my_labextension_demo/_version.py
my_labextension_demo-1.0.3.data/data/share/jupyter/labextensions/my-labextension-demo/package.json
my_labextension_demo-1.0.3.data/data/share/jupyter/labextensions/my-labextension-demo/schemas/my-labextension-demo/package.json.orig
my_labextension_demo-1.0.3.data/data/share/jupyter/labextensions/my-labextension-demo/schemas/my-labextension-demo/plugin.json
my_labextension_demo-1.0.3.data/data/share/jupyter/labextensions/my-labextension-demo/static/568.b6a88c5b3cd181be9505.js
my_labextension_demo-1.0.3.data/data/share/jupyter/labextensions/my-labextension-demo/static/747.1b8fd0ee47d900ebc630.js
my_labextension_demo-1.0.3.data/data/share/jupyter/labextensions/my-labextension-demo/static/remoteEntry.ff39d0d51412ea6b92f9.js
my_labextension_demo-1.0.3.data/data/share/jupyter/labextensions/my-labextension-demo/static/style.js
my_labextension_demo-1.0.3.data/data/share/jupyter/labextensions/my-labextension-demo/static/third-party-licenses.json
my_labextension_demo-1.0.3.data/data/share/jupyter/labextensions/my-labextension-demo/install.json
my_labextension_demo-1.0.3.dist-info/METADATA
my_labextension_demo-1.0.3.dist-info/WHEEL
my_labextension_demo-1.0.3.dist-info/entry_points.txt
my_labextension_demo-1.0.3.dist-info/licenses/LICENSE
my_labextension_demo-1.0.3.dist-info/RECORD
